comment.py
accepts/__init__.py
afk_tracker/__init__.py
afk_tracker/apps.py
afk_tracker/classes.py
afk_tracker/models.py
afk_tracker/setup.py
afk_tracker/migrations/0001_initial.py
afk_tracker/migrations/__init__.py
applescript/__init__.py
applescript/tell.py
badge/__init__.py
cached/__init__.py
ccmenu/__init__.py
ccmenu/preferences.py
ccmenu/restart.py
ccmenu/projects/__init__.py
ccmenu/projects/add.py
ccmenu/projects/clear.py
ccmenu/projects/names.py
ccmenu/projects/rm.py
ccmenu/projects/urls.py
ccmenu/travis/__init__.py
ccmenu/travis/add.py
ccmenu/travis/clear.py
ccmenu/travis/set.py
chmod/__init__.py
chmod/check.py
chmod/make.py
classifiers/__init__.py
classifiers_generator/__init__.py
classifiers_generator/__main__.py
cls/__init__.py
columnate/__init__.py
connection/__init__.py
control_characters/__init__.py
cp/__init__.py
created_by/__init__.py
created_by/middleware.py
detect/__init__.py
dict/__init__.py
direnv/__init__.py
django_admin_parent_filter/__init__.py
django_class/__init__.py
django_class/apps.py
django_class/models.py
django_class/migrations/0001_initial.py
django_class/migrations/__init__.py
django_datetime_elapsed_field/__init__.py
django_github_pages/__init__.py
django_github_pages/apps.py
django_github_pages/models.py
django_github_pages/setup.py
django_github_pages/migrations/0001_initial.py
django_github_pages/migrations/__init__.py
django_github_pages/templatetags/__init__.py
django_github_pages/templatetags/topics.py
django_launchd/__init__.py
django_launchd/apps.py
django_launchd/models.py
django_launchd/migrations/0001_initial.py
django_launchd/migrations/0002_auto_20190303_1704.py
django_launchd/migrations/0003_remove_plist_label.py
django_launchd/migrations/__init__.py
django_libraries/__init__.py
django_libraries/templatetags/__init__.py
django_libraries/templatetags/bootstrap-toggle.py
django_libraries/templatetags/bootstrap.py
django_libraries/templatetags/fontawesome.py
django_libraries/templatetags/jquery.py
github_description-2019.3.22.dist-info/METADATA
github_description-2019.3.22.dist-info/WHEEL
github_description-2019.3.22.dist-info/top_level.txt
github_description-2019.3.22.dist-info/RECORD
