Metadata-Version: 2.1
Name: github-description
Version: 2019.3.22
Summary: get/set github repo description
Home-page: https://github.com/looking-for-a-job/github-description.py
License: UNKNOWN
Keywords: github
Platform: UNKNOWN
Classifier: License :: Public Domain
Classifier: Operating System :: OS Independent
Classifier: Programming Language :: Python
Classifier: Programming Language :: Python :: 2
Classifier: Programming Language :: Python :: 2.7
Classifier: Programming Language :: Python :: 3
Classifier: Programming Language :: Python :: 3.4
Classifier: Programming Language :: Python :: 3.5
Classifier: Programming Language :: Python :: 3.6
Classifier: Topic :: Software Development
Requires-Dist: PyGithub
Requires-Dist: click
Requires-Dist: public
Requires-Dist: setuptools
